ribogadgets/__init__.py
ribogadgets/_version.py
ribogadgets/create.py
ribogadgets/dump.py
ribogadgets/info.py
ribogadgets/merge.py
ribogadgets/metadata.py
ribogadgets/plot.py
ribogadgets/ribo.py
ribogadgets/rnaseq.py
ribogadgets/settings.py
ribogadgets/cli/__init__.py
ribogadgets/cli/create.py
ribogadgets/cli/dump.py
ribogadgets/cli/info.py
ribogadgets/cli/main.py
ribogadgets/cli/merge.py
ribogadgets/cli/metadata.py
ribogadgets/cli/plot.py
ribogadgets/cli/rnaseq.py
ribogadgets/core/__init__.py
ribogadgets/core/aggregate_by_length.py
ribogadgets/core/coverage.py
ribogadgets/core/create_experiment.py
ribogadgets/core/exceptions.py
ribogadgets/core/get_gadgets.py
ribogadgets/core/metagene.py
ribogadgets/core/quantify.py
ribogadgets/core/region_counts.py
ribogadgets/core/verify.py
ribogadgets/core/write_profile.py
ribogadgets/io/__init__.py
ribogadgets/io/dump_coverage.py
ribogadgets/io/file.py
ribogadgets/io/metadata.py
ribogadgets/io/read_line_chunks.py
ribogadgets/io/separate_by_length.py
ribogadgets/io/write_profile.py
tests/__init__.py
tests/aggregate_by_length_test.py
tests/cli_create_test.py
tests/cli_dump_test.py
tests/cli_merge_test.py
tests/cli_plot_test.py
tests/cli_rnaseq_test.py
tests/coverage_test.py
tests/create_experiment_test.py
tests/create_test.py
tests/dump_test.py
tests/get_gadgets_test.py
tests/io_test.py
tests/merge_test.py
tests/metadata_test.py
tests/metagene_test.py
tests/multilength_test_data.py
tests/quantify_test.py
tests/region_counts_test.py
tests/ribo_api_test.py
tests/rnaseq_test.py
tests/test_data.py
ribogadgets-0.0.0.dist-info/LICENSE
ribogadgets-0.0.0.dist-info/METADATA
ribogadgets-0.0.0.dist-info/WHEEL
ribogadgets-0.0.0.dist-info/entry_points.txt
ribogadgets-0.0.0.dist-info/top_level.txt
ribogadgets-0.0.0.dist-info/RECORD
