Metadata-Version: 2.1
Name: ribogadgets
Version: 0.0.0
Summary: Hierarchichal data format based on hdf5 for ribosome profiling data
Home-page: UNKNOWN
Author: Hakan Ozadam
License: MIT
Platform: UNKNOWN
Classifier: Development Status :: 2 - Pre-Alpha
Classifier: Operating System :: OS Independent
Classifier: Programming Language :: Python
Classifier: Programming Language :: Python :: 3
Classifier: Programming Language :: Python :: 3.6
Classifier: Programming Language :: Python :: 3.7
Requires-Dist: numpy (>=1.16.1)
Requires-Dist: pandas (>=0.24.1)
Requires-Dist: click (==7.0)
Requires-Dist: h5py (>=2.9.0)
Requires-Dist: matplotlib (>=3.0.2)
Requires-Dist: multiprocess (>=0.70.7)
Requires-Dist: pysam (>=0.15.0)
Requires-Dist: pyyaml (==5.1)
